layers/__init__.py
layers/activation.py
layers/attention.py
layers/base.py
layers/decoder.py
layers/dense.py
layers/embedding.py
layers/flatten.py
layers/layernorm.py
layers/multihead_attention.py
layers/position_encoding.py
layers/transfomer.py
losses/__init__.py
losses/cross_entropy.py
models/__init__.py
models/base.py
models/model_with_adam.py
models/sequential.py
optimizers/__init__.py
pq/__init__.py
pq/layers/__init__.py
pq/layers/activation.py
pq/layers/attention.py
pq/layers/base.py
pq/layers/decoder.py
pq/layers/dense.py
pq/layers/embedding.py
pq/layers/flatten.py
pq/layers/layernorm.py
pq/layers/multihead_attention.py
pq/layers/position_encoding.py
pq/layers/transfomer.py
pq/losses/__init__.py
pq/losses/cross_entropy.py
pq/models/__init__.py
pq/models/base.py
pq/models/model_with_adam.py
pq/models/sequential.py
pq_nn/__init__.py
pq_nn/layers/__init__.py
pq_nn/layers/activation.py
pq_nn/layers/attention.py
pq_nn/layers/base.py
pq_nn/layers/decoder.py
pq_nn/layers/dense.py
pq_nn/layers/embedding.py
pq_nn/layers/flatten.py
pq_nn/layers/layernorm.py
pq_nn/layers/multihead_attention.py
pq_nn/layers/position_encoding.py
pq_nn/layers/transfomer.py
pq_nn/losses/__init__.py
pq_nn/losses/cross_entropy.py
pq_nn/models/__init__.py
pq_nn/models/base.py
pq_nn/models/model_with_adam.py
pq_nn/models/sequential.py
pq_nn-0.1.dist-info/METADATA
pq_nn-0.1.dist-info/WHEEL
pq_nn-0.1.dist-info/top_level.txt
pq_nn-0.1.dist-info/RECORD
