Metadata-Version: 2.2
Name: pq_nn
Version: 0.1
Requires-Dist: numpy
Dynamic: requires-dist
